<?xml version="1.0" encoding="utf-8"?>
<LanguageData>
  <!--The following translations were generated by https://www.deepl.com/-->
  <!-- EN: Activating Osiris casket. -->
  <RD_ActivateOsirisCasket.reportString>Aktivieren der Osiris-Schatulle.</RD_ActivateOsirisCasket.reportString>
  <!-- EN: Searching for stargates. -->
  <RD_DiscoverStargates.reportString>Auf der Suche nach Sternentoren.</RD_DiscoverStargates.reportString>
  <!-- EN: Booting Hologram. -->
  <RD_LoadIntoEmitter.reportString>Bootendes Hologramm.</RD_LoadIntoEmitter.reportString>
  <!-- EN: carefully milking TargetA. -->
  <RD_MandatoryMilk.reportString>sorgfältig melken TargetA.</RD_MandatoryMilk.reportString>
  <!-- EN: Negotiating. -->
  <RD_Negotiate.reportString>Verhandeln.</RD_Negotiate.reportString>
  <!-- EN: Praying. -->
  <RD_PrayAtObject.reportString>Beten.</RD_PrayAtObject.reportString>
  <!-- EN: Performing battle prayer. -->
  <RD_PsychicPrayer.reportString>Durchführung von Kampfgebeten.</RD_PsychicPrayer.reportString>
  <!-- EN: Making sacrifice. -->
  <RD_SacrificeAtAltar.reportString>Opfer bringen.</RD_SacrificeAtAltar.reportString>
  <!-- EN: HoloScanning body. -->
  <RD_ScanAtEmitter.reportString>HoloScanning Körper.</RD_ScanAtEmitter.reportString>
  <!-- EN: Storing body in casket. -->
  <RD_TakeToOsirisCasket.reportString>Lagerung der Leiche im Sarg.</RD_TakeToOsirisCasket.reportString>
  <!-- EN: Entering Stargate. -->
  <RD_TravelThroughStargate.reportString>Stargate betreten.</RD_TravelThroughStargate.reportString>
  <!-- EN: using computer. -->
  <RD_UseComputer.reportString>Computer benutzen.</RD_UseComputer.reportString>
</LanguageData>
